<?xml version="1.0" encoding="utf-8"?>
<Deliveries>
  <Delivery>
    <Id>1</Id>
    <OrderId>50</OrderId>
    <CourierId>520149191</CourierId>
    <DeliveryType>OnFoot</DeliveryType>
    <DeliveryStartTime>2026-01-13T12:26:39</DeliveryStartTime>
    <ActualDistance>2.485</ActualDistance>
  </Delivery>
  <Delivery>
    <Id>3</Id>
    <OrderId>40</OrderId>
    <CourierId>715178072</CourierId>
    <DeliveryType>Car</DeliveryType>
    <DeliveryStartTime>2026-01-14T19:03:39</DeliveryStartTime>
    <ActualDistance>3.432</ActualDistance>
  </Delivery>
  <Delivery>
    <Id>4</Id>
    <OrderId>38</OrderId>
    <CourierId>587218394</CourierId>
    <DeliveryType>Bicycle</DeliveryType>
    <DeliveryStartTime>2026-01-15T07:36:39</DeliveryStartTime>
    <ActualDistance>1.297</ActualDistance>
  </Delivery>
  <Delivery>
    <Id>5</Id>
    <OrderId>49</OrderId>
    <CourierId>424189769</CourierId>
    <DeliveryType>OnFoot</DeliveryType>
    <DeliveryStartTime>2026-01-15T10:13:39</DeliveryStartTime>
    <ActualDistance>4.932</ActualDistance>
  </Delivery>
  <Delivery>
    <Id>6</Id>
    <OrderId>16</OrderId>
    <CourierId>321182901</CourierId>
    <DeliveryType>Car</DeliveryType>
    <DeliveryStartTime>2026-01-16T03:46:39</DeliveryStartTime>
    <ActualDistance>4.609</ActualDistance>
  </Delivery>
  <Delivery>
    <Id>7</Id>
    <OrderId>39</OrderId>
    <CourierId>375174378</CourierId>
    <DeliveryType>Motorcycle</DeliveryType>
    <DeliveryStartTime>2026-01-16T08:22:39</DeliveryStartTime>
    <ActualDistance>1.845</ActualDistance>
  </Delivery>
  <Delivery>
    <Id>8</Id>
    <OrderId>37</OrderId>
    <CourierId>659907687</CourierId>
    <DeliveryType>OnFoot</DeliveryType>
    <DeliveryStartTime>2026-01-16T11:02:39</DeliveryStartTime>
    <ActualDistance>1.281</ActualDistance>
  </Delivery>
  <Delivery>
    <Id>9</Id>
    <OrderId>24</OrderId>
    <CourierId>479663077</CourierId>
    <DeliveryType>OnFoot</DeliveryType>
    <DeliveryStartTime>2026-01-16T14:06:39</DeliveryStartTime>
    <ActualDistance>1.663</ActualDistance>
  </Delivery>
  <Delivery>
    <Id>11</Id>
    <OrderId>25</OrderId>
    <CourierId>417445238</CourierId>
    <DeliveryType>Bicycle</DeliveryType>
    <DeliveryStartTime>2026-01-16T16:56:39</DeliveryStartTime>
    <ActualDistance>2.984</ActualDistance>
    <DeliveryEndType>Delivered</DeliveryEndType>
    <DeliveryEndTime>2026-01-16T17:56:39</DeliveryEndTime>
  </Delivery>
  <Delivery>
    <Id>12</Id>
    <OrderId>30</OrderId>
    <CourierId>686228824</CourierId>
    <DeliveryType>Motorcycle</DeliveryType>
    <DeliveryStartTime>2026-01-17T06:22:39</DeliveryStartTime>
    <ActualDistance>3.051</ActualDistance>
    <DeliveryEndType>RecipientNotFound</DeliveryEndType>
    <DeliveryEndTime>2026-01-17T07:04:39</DeliveryEndTime>
  </Delivery>
  <Delivery>
    <Id>13</Id>
    <OrderId>45</OrderId>
    <CourierId>349068643</CourierId>
    <DeliveryType>Car</DeliveryType>
    <DeliveryStartTime>2026-01-17T02:39:39</DeliveryStartTime>
    <ActualDistance>2.997</ActualDistance>
    <DeliveryEndType>RecipientNotFound</DeliveryEndType>
    <DeliveryEndTime>2026-01-17T03:35:39</DeliveryEndTime>
  </Delivery>
  <Delivery>
    <Id>14</Id>
    <OrderId>28</OrderId>
    <CourierId>417445238</CourierId>
    <DeliveryType>Bicycle</DeliveryType>
    <DeliveryStartTime>2026-01-17T19:17:39</DeliveryStartTime>
    <ActualDistance>3.868</ActualDistance>
    <DeliveryEndType>Cancelled</DeliveryEndType>
    <DeliveryEndTime>2026-01-17T19:53:39</DeliveryEndTime>
  </Delivery>
  <Delivery>
    <Id>15</Id>
    <OrderId>18</OrderId>
    <CourierId>287606653</CourierId>
    <DeliveryType>Bicycle</DeliveryType>
    <DeliveryStartTime>2026-01-17T14:39:39</DeliveryStartTime>
    <ActualDistance>4.62</ActualDistance>
    <DeliveryEndType>Delivered</DeliveryEndType>
    <DeliveryEndTime>2026-01-17T15:33:39</DeliveryEndTime>
  </Delivery>
  <Delivery>
    <Id>16</Id>
    <OrderId>41</OrderId>
    <CourierId>686228824</CourierId>
    <DeliveryType>Motorcycle</DeliveryType>
    <DeliveryStartTime>2026-01-18T05:12:39</DeliveryStartTime>
    <ActualDistance>12.122</ActualDistance>
    <DeliveryEndType>CustomerRefused</DeliveryEndType>
    <DeliveryEndTime>2026-01-18T05:47:39</DeliveryEndTime>
  </Delivery>
  <Delivery>
    <Id>17</Id>
    <OrderId>17</OrderId>
    <CourierId>642201707</CourierId>
    <DeliveryType>Bicycle</DeliveryType>
    <DeliveryStartTime>2026-01-17T13:30:39</DeliveryStartTime>
    <ActualDistance>2.406</ActualDistance>
    <DeliveryEndType>Delivered</DeliveryEndType>
    <DeliveryEndTime>2026-01-17T13:58:39</DeliveryEndTime>
  </Delivery>
  <Delivery>
    <Id>18</Id>
    <OrderId>1</OrderId>
    <CourierId>686228824</CourierId>
    <DeliveryType>Motorcycle</DeliveryType>
    <DeliveryStartTime>2026-01-19T00:52:39</DeliveryStartTime>
    <ActualDistance>3.626</ActualDistance>
    <DeliveryEndType>Delivered</DeliveryEndType>
    <DeliveryEndTime>2026-01-19T02:00:39</DeliveryEndTime>
  </Delivery>
  <Delivery>
    <Id>19</Id>
    <OrderId>6</OrderId>
    <CourierId>287606653</CourierId>
    <DeliveryType>Bicycle</DeliveryType>
    <DeliveryStartTime>2026-01-18T05:47:39</DeliveryStartTime>
    <ActualDistance>2.679</ActualDistance>
    <DeliveryEndType>Delivered</DeliveryEndType>
    <DeliveryEndTime>2026-01-18T06:04:39</DeliveryEndTime>
  </Delivery>
  <Delivery>
    <Id>20</Id>
    <OrderId>44</OrderId>
    <CourierId>287606653</CourierId>
    <DeliveryType>Bicycle</DeliveryType>
    <DeliveryStartTime>2026-01-19T22:16:39</DeliveryStartTime>
    <ActualDistance>3.577</ActualDistance>
    <DeliveryEndType>Failed</DeliveryEndType>
    <DeliveryEndTime>2026-01-19T22:45:39</DeliveryEndTime>
  </Delivery>
  <Delivery>
    <Id>21</Id>
    <OrderId>44</OrderId>
    <CourierId>417445238</CourierId>
    <DeliveryType>Bicycle</DeliveryType>
    <DeliveryStartTime>2026-01-20T01:52:39</DeliveryStartTime>
    <ActualDistance>3.028</ActualDistance>
    <DeliveryEndType>Delivered</DeliveryEndType>
    <DeliveryEndTime>2026-01-20T02:20:39</DeliveryEndTime>
  </Delivery>
  <Delivery>
    <Id>22</Id>
    <OrderId>26</OrderId>
    <CourierId>349068643</CourierId>
    <DeliveryType>Car</DeliveryType>
    <DeliveryStartTime>2026-01-20T08:07:39</DeliveryStartTime>
    <ActualDistance>4.113</ActualDistance>
    <DeliveryEndType>Delivered</DeliveryEndType>
    <DeliveryEndTime>2026-01-20T08:34:39</DeliveryEndTime>
  </Delivery>
  <Delivery>
    <Id>23</Id>
    <OrderId>46</OrderId>
    <CourierId>287606653</CourierId>
    <DeliveryType>Bicycle</DeliveryType>
    <DeliveryStartTime>2026-01-20T16:08:39</DeliveryStartTime>
    <ActualDistance>3.19</ActualDistance>
    <DeliveryEndType>Delivered</DeliveryEndType>
    <DeliveryEndTime>2026-01-20T16:40:39</DeliveryEndTime>
  </Delivery>
  <Delivery>
    <Id>24</Id>
    <OrderId>33</OrderId>
    <CourierId>686228824</CourierId>
    <DeliveryType>Motorcycle</DeliveryType>
    <DeliveryStartTime>2026-01-20T17:58:39</DeliveryStartTime>
    <ActualDistance>2.395</ActualDistance>
    <DeliveryEndType>Delivered</DeliveryEndType>
    <DeliveryEndTime>2026-01-20T18:28:39</DeliveryEndTime>
  </Delivery>
  <Delivery>
    <Id>25</Id>
    <OrderId>3</OrderId>
    <CourierId>384371421</CourierId>
    <DeliveryType>Motorcycle</DeliveryType>
    <DeliveryStartTime>2026-01-21T07:06:39</DeliveryStartTime>
    <ActualDistance>2.982</ActualDistance>
    <DeliveryEndType>Delivered</DeliveryEndType>
    <DeliveryEndTime>2026-01-21T07:50:39</DeliveryEndTime>
  </Delivery>
  <Delivery>
    <Id>26</Id>
    <OrderId>48</OrderId>
    <CourierId>384371421</CourierId>
    <DeliveryType>Motorcycle</DeliveryType>
    <DeliveryStartTime>2026-01-21T03:38:39</DeliveryStartTime>
    <ActualDistance>2.443</ActualDistance>
    <DeliveryEndType>Delivered</DeliveryEndType>
    <DeliveryEndTime>2026-01-21T04:27:39</DeliveryEndTime>
  </Delivery>
  <Delivery>
    <Id>27</Id>
    <OrderId>11</OrderId>
    <CourierId>686228824</CourierId>
    <DeliveryType>Motorcycle</DeliveryType>
    <DeliveryStartTime>2026-01-21T11:50:39</DeliveryStartTime>
    <ActualDistance>5.231</ActualDistance>
    <DeliveryEndType>Delivered</DeliveryEndType>
    <DeliveryEndTime>2026-01-21T12:53:39</DeliveryEndTime>
  </Delivery>
  <Delivery>
    <Id>28</Id>
    <OrderId>22</OrderId>
    <CourierId>287606653</CourierId>
    <DeliveryType>Bicycle</DeliveryType>
    <DeliveryStartTime>2026-01-21T18:56:39</DeliveryStartTime>
    <ActualDistance>6.243</ActualDistance>
    <DeliveryEndType>CustomerRefused</DeliveryEndType>
    <DeliveryEndTime>2026-01-21T19:16:39</DeliveryEndTime>
  </Delivery>
  <Delivery>
    <Id>29</Id>
    <OrderId>32</OrderId>
    <CourierId>417445238</CourierId>
    <DeliveryType>Bicycle</DeliveryType>
    <DeliveryStartTime>2026-01-21T18:53:39</DeliveryStartTime>
    <ActualDistance>6.306</ActualDistance>
    <DeliveryEndType>Delivered</DeliveryEndType>
    <DeliveryEndTime>2026-01-21T19:36:39</DeliveryEndTime>
  </Delivery>
  <Delivery>
    <Id>30</Id>
    <OrderId>34</OrderId>
    <CourierId>349068643</CourierId>
    <DeliveryType>Car</DeliveryType>
    <DeliveryStartTime>2026-01-21T19:20:39</DeliveryStartTime>
    <ActualDistance>2.321</ActualDistance>
    <DeliveryEndType>Delivered</DeliveryEndType>
    <DeliveryEndTime>2026-01-21T19:59:39</DeliveryEndTime>
  </Delivery>
  <Delivery>
    <Id>31</Id>
    <OrderId>47</OrderId>
    <CourierId>642201707</CourierId>
    <DeliveryType>Bicycle</DeliveryType>
    <DeliveryStartTime>2026-01-21T19:58:39</DeliveryStartTime>
    <ActualDistance>2.927</ActualDistance>
    <DeliveryEndType>Delivered</DeliveryEndType>
    <DeliveryEndTime>2026-01-21T21:00:39</DeliveryEndTime>
  </Delivery>
  <Delivery>
    <Id>10</Id>
    <OrderId>9</OrderId>
    <CourierId>317263035</CourierId>
    <DeliveryType>OnFoot</DeliveryType>
    <DeliveryStartTime>2026-01-16T09:46:39</DeliveryStartTime>
    <ActualDistance>3.111</ActualDistance>
    <DeliveryEndType>Cancelled</DeliveryEndType>
    <DeliveryEndTime>2030-01-20T20:48:39</DeliveryEndTime>
  </Delivery>
  <Delivery>
    <Id>2</Id>
    <OrderId>10</OrderId>
    <CourierId>228742303</CourierId>
    <DeliveryType>Car</DeliveryType>
    <DeliveryStartTime>2026-01-13T15:07:39</DeliveryStartTime>
    <ActualDistance>2.08</ActualDistance>
    <DeliveryEndType>Cancelled</DeliveryEndType>
    <DeliveryEndTime>2030-01-20T20:48:39</DeliveryEndTime>
  </Delivery>
</Deliveries>